ezutils/__init__.py
ezutils/colors.py
ezutils/files.py
ezutils/progress.py
ezutils-0.0.5.dist-info/METADATA
ezutils-0.0.5.dist-info/WHEEL
ezutils-0.0.5.dist-info/top_level.txt
ezutils-0.0.5.dist-info/RECORD
