Metadata-Version: 2.1
Name: ezutils
Version: 0.0.5
Summary: Utils to save your time on python coding
Home-page: https://github.com/caojianfeng/ezutils
Author: JeffreyCao
Author-email: jeffreycao1024@gmail.com
License: MIT Licence
Keywords: color,file,progress,ezutils
Platform: any
Classifier: Programming Language :: Python :: 3
Classifier: License :: OSI Approved :: MIT License
Classifier: Operating System :: OS Independent
Requires-Python: >=3.6
